MANIFEST.in
README.rst
setup.py
collective/__init__.py
collective/__init__.pyc
collective.ptg.contentflow.egg-info/PKG-INFO
collective.ptg.contentflow.egg-info/SOURCES.txt
collective.ptg.contentflow.egg-info/dependency_links.txt
collective.ptg.contentflow.egg-info/entry_points.txt
collective.ptg.contentflow.egg-info/namespace_packages.txt
collective.ptg.contentflow.egg-info/not-zip-safe
collective.ptg.contentflow.egg-info/requires.txt
collective.ptg.contentflow.egg-info/top_level.txt
collective/ptg/__init__.py
collective/ptg/__init__.pyc
collective/ptg/contentflow/__init__.py
collective/ptg/contentflow/__init__.pyc
collective/ptg/contentflow/configure.zcml
collective/ptg/contentflow/contentflow.pt
collective/ptg/contentflow/i18n.sh
collective/ptg/contentflow/locales/collective.ptg.contentflow.pot
collective/ptg/contentflow/locales/manual.pot
collective/ptg/contentflow/locales/de/LC_MESSAGES/collective.ptg.contentflow.po
collective/ptg/contentflow/locales/es/LC_MESSAGES/collective.ptg.contentflow.po
collective/ptg/contentflow/locales/eu/LC_MESSAGES/collective.ptg.contentflow.po
collective/ptg/contentflow/locales/fi/LC_MESSAGES/collective.ptg.contentflow.po
collective/ptg/contentflow/locales/fr/LC_MESSAGES/collective.ptg.contentflow.po
collective/ptg/contentflow/locales/it/LC_MESSAGES/collective.ptg.contentflow.po
collective/ptg/contentflow/locales/nl/LC_MESSAGES/collective.ptg.contentflow.po
collective/ptg/contentflow/locales/no/LC_MESSAGES/collective.ptg.contentflow.po
collective/ptg/contentflow/locales/pt_BR/LC_MESSAGES/collective.ptg.contentflow.po
collective/ptg/contentflow/resources/ContentFlowAddOn_black.css
collective/ptg/contentflow/resources/ContentFlowAddOn_black.js
collective/ptg/contentflow/resources/ContentFlowAddOn_gallery.js
collective/ptg/contentflow/resources/ContentFlowAddOn_lightbox.js
collective/ptg/contentflow/resources/ContentFlowAddOn_roundabout.js
collective/ptg/contentflow/resources/ContentFlowAddOn_screwdriver.js
collective/ptg/contentflow/resources/ContentFlowAddOn_slideshow.css
collective/ptg/contentflow/resources/ContentFlowAddOn_slideshow.js
collective/ptg/contentflow/resources/ContentFlowAddOn_white.css
collective/ptg/contentflow/resources/ContentFlowAddOn_white.js
collective/ptg/contentflow/resources/contentflow.css
collective/ptg/contentflow/resources/contentflow.js
collective/ptg/contentflow/resources/contentflow_src.css
