Metadata-Version: 1.0
Name: collective.ptg.contentflow
Version: 1.0.3
Summary: UNKNOWN
Home-page: https://github.com/collective/collective.ptg.contentflow
Author: Nathan Van Gheem
Author-email: vangheem@gmail.com
License: GPL
Keywords: vangheem@gmail.com
Platform: UNKNOWN
Classifier: Framework :: Plone
Classifier: Programming Language :: Python
